minidict/__init__.py
minidict-0.0.1.dist-info/LICENSE
minidict-0.0.1.dist-info/METADATA
minidict-0.0.1.dist-info/WHEEL
minidict-0.0.1.dist-info/top_level.txt
minidict-0.0.1.dist-info/RECORD
