Metadata-Version: 2.1
Name: minidict
Version: 0.0.1
Summary: Minimal read-only dictionary
Home-page: https://github.com/numpde/minidict
Author: RA
Author-email: numpde@null.net
License: UNKNOWN
Keywords: read-only python dict
Platform: UNKNOWN
Classifier: Programming Language :: Python :: 3
Classifier: License :: OSI Approved :: MIT License
Classifier: Operating System :: OS Independent
Requires-Python: >=3.6
